qase/tavern/__init__.py
qase/tavern/conftest.py
qase/tavern/context_manager.py
qase/tavern/options.py
qase/tavern/plugin.py
qase_tavern-3.0.0.dist-info/licenses/LICENSE.txt
qase_tavern-3.0.0.dist-info/METADATA
qase_tavern-3.0.0.dist-info/WHEEL
qase_tavern-3.0.0.dist-info/entry_points.txt
qase_tavern-3.0.0.dist-info/top_level.txt
qase_tavern-3.0.0.dist-info/RECORD
