Metadata-Version: 2.4
Name: qase-tavern
Version: 3.0.0
Summary: Qase Tavern Plugin for Qase TestOps and Qase Report
Author-email: Qase Team <support@qase.io>
Project-URL: Homepage, https://qase.io
Project-URL: Repository, https://github.com/qase-tms/qase-python/tree/main/qase-tavern
Project-URL: Documentation, https://developers.qase.io
Keywords: qase,tavern,plugin,testops,report,qase reporting,test observability
Classifier: Development Status :: 5 - Production/Stable
Classifier: Programming Language :: Python
Classifier: Framework :: Pytest
Classifier: Intended Audience :: Developers
Classifier: License :: OSI Approved :: Apache Software License
Classifier: Topic :: Software Development :: Quality Assurance
Classifier: Topic :: Software Development :: Testing
Classifier: Programming Language :: Python :: 3
Classifier: Programming Language :: Python :: 3 :: Only
Classifier: Programming Language :: Python :: 3.9
Classifier: Programming Language :: Python :: 3.10
Classifier: Programming Language :: Python :: 3.11
Classifier: Programming Language :: Python :: 3.12
Classifier: Programming Language :: Python :: 3.13
Requires-Python: >=3.9
License-File: LICENSE.txt
Requires-Dist: qase-python-commons~=5.0.0
Requires-Dist: pytest<7.3,>=7
Requires-Dist: filelock>=3.12.2
Requires-Dist: more_itertools
Provides-Extra: testing
Requires-Dist: pytest; extra == "testing"
Requires-Dist: pytest-cov; extra == "testing"
Dynamic: license-file
